LICENSE
README.md
setup.py
./onesnipe/__init__.py
./onesnipe/__main__.py
./onesnipe/auth.py
./onesnipe/console.py
./onesnipe/constants.py
./onesnipe/functions.py
./onesnipe/requests/__init__.py
./onesnipe/requests/formatter.py
./onesnipe/requests/request.py
./onesnipe/sniper/__init__.py
./onesnipe/sniper/offset.py
./onesnipe/sniper/sniper.py
OneSnipe.egg-info/PKG-INFO
OneSnipe.egg-info/SOURCES.txt
OneSnipe.egg-info/dependency_links.txt
OneSnipe.egg-info/entry_points.txt
OneSnipe.egg-info/requires.txt
OneSnipe.egg-info/top_level.txt